api.py
clickup_utils.py
main.py
rag_utils.py
schemas.py
settings.py
utils.py
routers/audio_router.py
routers/clickup_router.py
routers/cron_router.py
routers/frontend_router.py
routers/rag_router.py
routers/text_router.py
templates/chat.html
templates/graph_viewer.html
templates/home.html
campaign_generator-0.1.9.dist-info/METADATA
campaign_generator-0.1.9.dist-info/WHEEL
campaign_generator-0.1.9.dist-info/entry_points.txt
campaign_generator-0.1.9.dist-info/top_level.txt
campaign_generator-0.1.9.dist-info/RECORD
