Metadata-Version: 2.4
Name: campaign-generator
Version: 0.1.9
Summary: A FastAPI service for campaign generation, competitor research, and audio content.
Author-email: James Twose <contact@jamestwose.com>
Requires-Python: >=3.10
Requires-Dist: fastapi
Requires-Dist: uvicorn
Requires-Dist: requests
Requires-Dist: torch
Requires-Dist: torchvision
Requires-Dist: torchaudio
Requires-Dist: whisper-mps
Requires-Dist: python-multipart
Requires-Dist: pydantic-settings
Requires-Dist: crawl4ai
Requires-Dist: playwright
Requires-Dist: playwright_stealth
Requires-Dist: lightrag-hku
Requires-Dist: feedparser
